LiteClashProMan/__init__.py
LiteClashProMan/api/__init__.py
LiteClashProMan/config.py
LiteClashProMan/log.py
LiteClashProMan/main.py
LiteClashProMan/model/clash/__init__.py
LiteClashProMan/model/clash/proxy.py
LiteClashProMan/model/clash/proxygroup.py
LiteClashProMan/model/clash/ruleprovider.py
LiteClashProMan/static/config.exp.yaml
LiteClashProMan/static/template/blacklist.yaml
LiteClashProMan/static/template/whitelist.yaml
LiteClashProMan/subscribe/__init__.py
LiteClashProMan/subscribe/base64.py
LiteClashProMan/subscribe/clash.py
LiteClashProMan/subscribe/jms.py
LiteClashProMan/utils.py
liteclashproman-0.5.2.dist-info/METADATA
liteclashproman-0.5.2.dist-info/WHEEL
liteclashproman-0.5.2.dist-info/entry_points.txt
liteclashproman-0.5.2.dist-info/licenses/LICENSE
liteclashproman-0.5.2.dist-info/RECORD
