Metadata-Version: 2.1
Name: LiteClashProMan
Version: 0.5.2
Summary: 生成并更新 clash 配置文件，并提供 http 下载和规则文件镜像下载。
Author-Email: Well404 <well_404@outlook.com>
License: APGL-3.0
Requires-Python: >=3.8
Requires-Dist: pyyaml>=6.0
Requires-Dist: fastapi[all]>=0.96.0
Requires-Dist: httpx>=0.24.1
Requires-Dist: APScheduler>=3.10.1
Requires-Dist: loguru>=0.7.0
Requires-Dist: sentry-sdk[fastapi]>=1.26.0; extra == "extra"
Provides-Extra: extra
